adafruit_ssd1683.py
adafruit_circuitpython_ssd1683-1.0.1.dist-info/licenses/LICENSE
adafruit_circuitpython_ssd1683-1.0.1.dist-info/METADATA
adafruit_circuitpython_ssd1683-1.0.1.dist-info/WHEEL
adafruit_circuitpython_ssd1683-1.0.1.dist-info/top_level.txt
adafruit_circuitpython_ssd1683-1.0.1.dist-info/RECORD
