Metadata-Version: 2.4
Name: adafruit-circuitpython-ssd1683
Version: 1.0.1
Summary: CircuitPython `displayio` driver for the SSD1683 epaper IC
Author-email: Adafruit Industries <circuitpython@adafruit.com>
License: MIT
Project-URL: Homepage, https://github.com/adafruit/Adafruit_CircuitPython_SSD1683
Keywords: adafruit,blinka,circuitpython,micropython,ssd1683,SSD1683
Classifier: Intended Audience :: Developers
Classifier: Topic :: Software Development :: Libraries
Classifier: Topic :: Software Development :: Embedded Systems
Classifier: Topic :: System :: Hardware
Classifier: License :: OSI Approved :: MIT License
Classifier: Programming Language :: Python :: 3
License-File: LICENSE
Requires-Dist: Adafruit-Blinka
Provides-Extra: optional
Dynamic: license-file
